cucon/main.py
cucon-0.1.0.dist-info/LICENSE
cucon-0.1.0.dist-info/METADATA
cucon-0.1.0.dist-info/WHEEL
cucon-0.1.0.dist-info/entry_points.txt
cucon-0.1.0.dist-info/RECORD
