Metadata-Version: 2.1
Name: cucon
Version: 0.1.0
Summary: Tool to build resources in public cloud
License: MIT
Author: Jakub Spórna
Author-email: jakub.sporna@gmail.com
Requires-Python: >=3.11,<4.0
Classifier: License :: OSI Approved :: MIT License
Classifier: Programming Language :: Python :: 3
Classifier: Programming Language :: Python :: 3.11
Classifier: Programming Language :: Python :: 3.12
Requires-Dist: boto3 (>=1.34.59,<2.0.0)
Requires-Dist: pydantic (>=2.6.3,<3.0.0)
